azure/mgmt/reservations/__init__.py
azure/mgmt/reservations/_azure_reservation_api.py
azure/mgmt/reservations/_configuration.py
azure/mgmt/reservations/_patch.py
azure/mgmt/reservations/_serialization.py
azure/mgmt/reservations/_vendor.py
azure/mgmt/reservations/_version.py
azure/mgmt/reservations/py.typed
azure/mgmt/reservations/aio/__init__.py
azure/mgmt/reservations/aio/_azure_reservation_api.py
azure/mgmt/reservations/aio/_configuration.py
azure/mgmt/reservations/aio/_patch.py
azure/mgmt/reservations/aio/_vendor.py
azure/mgmt/reservations/aio/operations/__init__.py
azure/mgmt/reservations/aio/operations/_azure_reservation_api_operations.py
azure/mgmt/reservations/aio/operations/_calculate_exchange_operations.py
azure/mgmt/reservations/aio/operations/_calculate_refund_operations.py
azure/mgmt/reservations/aio/operations/_exchange_operations.py
azure/mgmt/reservations/aio/operations/_operation_operations.py
azure/mgmt/reservations/aio/operations/_patch.py
azure/mgmt/reservations/aio/operations/_quota_operations.py
azure/mgmt/reservations/aio/operations/_quota_request_status_operations.py
azure/mgmt/reservations/aio/operations/_reservation_operations.py
azure/mgmt/reservations/aio/operations/_reservation_order_operations.py
azure/mgmt/reservations/aio/operations/_return_operations_operations.py
azure/mgmt/reservations/models/__init__.py
azure/mgmt/reservations/models/_azure_reservation_api_enums.py
azure/mgmt/reservations/models/_models_py3.py
azure/mgmt/reservations/models/_patch.py
azure/mgmt/reservations/operations/__init__.py
azure/mgmt/reservations/operations/_azure_reservation_api_operations.py
azure/mgmt/reservations/operations/_calculate_exchange_operations.py
azure/mgmt/reservations/operations/_calculate_refund_operations.py
azure/mgmt/reservations/operations/_exchange_operations.py
azure/mgmt/reservations/operations/_operation_operations.py
azure/mgmt/reservations/operations/_patch.py
azure/mgmt/reservations/operations/_quota_operations.py
azure_mgmt_reservations-2.3.0.dist-info/LICENSE
azure_mgmt_reservations-2.3.0.dist-info/METADATA
azure_mgmt_reservations-2.3.0.dist-info/WHEEL
azure_mgmt_reservations-2.3.0.dist-info/top_level.txt
azure_mgmt_reservations-2.3.0.dist-info/RECORD
